{"metadata":{"dataVersion":"2","matchId":"EUW1_5979941498","participants":["LzQXU7Q47e4h_oW0iiSygqQV0oxvcbuVOdZgr2NWbwH1DIEyry0rHIfUoKsuIafompjFGuIsdNtQLQ","fCWK7q6SFtQIL69YLVao0Yzy-lPUu0kKkGM_oOfyRNu75mCm7nriSk-JMVXs3VgJxQkOPR6ATq5_wQ","e2Wo4PGAcQDEOWeyS1srrOR4eNTedZylmJ6ndc_Vwf2fGx-EB6uWTv00DE81jLJWSW0EECX2MIBxtw","RMGAJeKP9eOfyXl0burUMaHFWmSxZLZU0J08dBCeUg6rHJn-DE8IlEGgAGLjd24uAVF01LqU6vk2Zw","pYYpa3eRU8O0fCkOU2mEcvCad-NMyRfZBkwfBAi0NzDB2__LfBLMlL-BfHWgqtqsBDyNQb4bzRkQfg","rgWIpBYEyQ8TC8wXyiJrIlXgSM1o77taGZp5bOzXhhOo4aDPcsgIbkHr9TSbpWdi1OM2S7TIVPGSGA","A_b8QEtbmOqikQjNisk0upEsWTEG5vHWldVXdGklQpd4CRJIPHXt8H9wfi7aAW_C6I095NyBsWJSGA","AfJnU8VZj-cpNDuhKFmluLnvZJgVxFR49OxlkBkBqRL-Y08V9W3IWFuT7FK0FFRDBaBWDa-lPttgdQ","bvxrxmuPyv8PjLzrV_fHRrjY0QEuRQ7XjAwA2fDm8Iu0A0xfKrnRBNehrXJx3I3rSMnfmUN3y3PrBg","nor02xlFnxQbf-rUDK9ElPt8rZBLX2027oxC66JkoyDK74pJA9TArWrY66jrQtaYxMiaZwpDinv78g"]},"info":{"gameCreation":1658424797000,"gameDuration":1317,"gameEndTimestamp":1658426359250,"gameId":5979941498,"gameMode":"ARAM","gameName":"teambuilder-match-5979941498","gameStartTimestamp":1658425041801,"gameType":"MATCHED_GAME","gameVersion":"12.13.453.3037","mapId":12,"participants":[{"assists":31,"baronKills":0,"basicPings":0,"bountyLevel":2,"challenges":{"12AssistStreakCount":0,"abilityUses":219,"acesBefore15Minutes":0,"alliedJungleMonsterKills":0,"baronTakedowns":0,"blastConeOppositeOpponentCount":0,"bountyGold":600,"buffsStolen":0,"completeSupportQuestInTime":0,"controlWardsPlaced":0,"damagePerMinute":1233.1220478093599,"damageTakenOnTeamPercentage":0.17350350410875948,"dancedWithRiftHerald":0,"deathsByEnemyChamps":15,"dodgeSkillShotsSmallWindow":1,"doubleAces":0,"dragonTakedowns":0,"earlyLaningPhaseGoldExpAdvantage":0,"effectiveHealAndShielding":0,"elderDragonKillsWithOpposingSoul":0,"elderDragonMultikills":0,"enemyChampionImmobilizations":0,"enemyJungleMonsterKills":0,"epicMonsterKillsNearEnemyJungler":0,"epicMonsterKillsWithin30SecondsOfSpawn":0,"epicMonsterSteals":0,"epicMonsterStolenWithoutSmite":0,"firstTurretKilledTime":536.5541941,"flawlessAces":0,"fullTeamTakedown":7,"gameLength":1317.6331278999999,"getTakedownsInAllLanesEarlyJungleAsLaner":0,"goldPerMinute":682.7779453887774,"hadOpenNexus":0,"highestCrowdControlScore":1,"immobilizeAndKillWithAlly":0,"initialBuffCount":0,"initialCrabCount":0,"jungleCsBefore10Minutes":0,"junglerTakedownsNearDamagedEpicMonster":0,"kTurretsDestroyedBeforePlatesFall":0,"kda":2.6,"killAfterHiddenWithAlly":9,"killParticipation":0.5131578947368421,"killedChampTookFullTeamDamageSurvived":0,"killsNearEnemyTurret":0,"killsOnOtherLanesEarlyJungleAsLaner":0,"killsOnRecentlyHealedByAramPack":0,"killsUnderOwnTurret":0,"killsWithHelpFromEpicMonster":0,"knockEnemyIntoTeamAndKill":0,"landSkillShotsEarlyGame":0,"laneMinionsFirst10Minutes":30,"laningPhaseGoldExpAdvantage":0,"legendaryCount":0,"lostAnInhibitor":1,"maxCsAdvantageOnLaneOpponent":30,"maxKillDeficit":7,"maxLevelLeadLaneOpponent":2,"moreEnemyJungleThanOpponent":-20,"multiKillOneSpell":0,"multiTurretRiftHeraldCount":0,"multikills":1,"multikillsAfterAggressiveFlash":0,"mythicItemUsed":6653,"outerTurretExecutesBefore10Minutes":0,"outnumberedKills":5,"outnumberedNexusKill":0,"perfectDragonSoulsTaken":0,"perfectGame":0,"pickKillWithAlly":27,"poroExplosions":0,"quickCleanse":0,"quickFirstTurret":0,"quickSoloKills":0,"riftHeraldTakedowns":0,"saveAllyFromDeath":0,"scuttleCrabKills":0,"skillshotsDodged":35,"skillshotsHit":0,"snowballsHit":5,"soloBaronKills":0,"soloKills":0,"stealthWardsPlaced":0,"survivedSingleDigitHpCount":0,"survivedThreeImmobilizesInFight":0,"takedownOnFirstTurret":0,"takedowns":39,"takedownsAfterGainingLevelAdvantage":0,"takedownsBeforeJungleMinionSpawn":0,"takedownsFirstXMinutes":26,"takedownsInAlcove":0,"takedownsInEnemyFountain":0,"teamBaronKills":0,"teamDamagePercentage":0.16810210379374052,"teamElderDragonKills":0,"teamRiftHeraldKills":0,"threeWardsOneSweeperCount":0,"tookLargeDamageSurvived":0,"turretPlatesTaken":0,"turretTakedowns":0,"turretsTakenWithRiftHerald":0,"twentyMinionsIn3SecondsCount":0,"unseenRecalls":0,"visionScoreAdvantageLaneOpponent":-1,"visionScorePerMinute":0,"wardTakedowns":0,"wardTakedownsBefore20M":0,"wardsGuarded":0},"champExperience":22938,"champLevel":18,"championId":30,"championName":"Karthus","championTransform":0,"consumablesPurchased":0,"damageDealtToBuildings":0,"damageDealtToObjectives":0,"damageDealtToTurrets":0,"damageSelfMitigated":16502,"deaths":15,"detectorWardsPlaced":0,"doubleKills":1,"dragonKills":0,"eligibleForProgression":true,"firstBloodAssist":false,"firstBloodKill":false,"firstTowerAssist":false,"firstTowerKill":false,"gameEndedInEarlySurrender":false,"gameEndedInSurrender":false,"goldEarned":14994,"goldSpent":14300,"individualPosition":"Invalid","inhibitorKills":0,"inhibitorTakedowns":1,"inhibitorsLost":2,"item0":6653,"item1":3157,"item2":4645,"item3":3020,"item4":3089,"item5":3916,"item6":2052,"itemsPurchased":18,"killingSprees":2,"kills":8,"lane":"TOP","largestCriticalStrike":0,"largestKillingSpree":2,"largestMultiKill":2,"longestTimeSpentLiving":105,"magicDamageDealt":73631,"magicDamageDealtToChampions":25219,"magicDamageTaken":16120,"neutralMinionsKilled":0,"nexusKills":0,"nexusLost":0,"nexusTakedowns":0,"objectivesStolen":0,"objectivesStolenAssists":0,"participantId":1,"pentaKills":0,"perks":{"statPerks":{"defense":5002,"flex":5008,"offense":5008},"styles":[{"description":"primaryStyle","selections":[{"perk":8128,"var1":2011,"var2":29,"var3":0},{"perk":8126,"var1":842,"var2":0,"var3":0},{"perk":8138,"var1":30,"var2":0,"var3":0},{"perk":8106,"var1":5,"var2":0,"var3":0}],"style":8100},{"description":"subStyle","selections":[{"perk":8009,"var1":4873,"var2":0,"var3":0},{"perk":8014,"var1":998,"var2":0,"var3":0}],"style":8000}]},"physicalDamageDealt":549,"physicalDamageDealtToChampions":147,"physicalDamageTaken":11361,"profileIcon":654,"puuid":"LzQXU7Q47e4h_oW0iiSygqQV0oxvcbuVOdZgr2NWbwH1DIEyry0rHIfUoKsuIafompjFGuIsdNtQLQ","quadraKills":0,"riotIdName":"","riotIdTagline":"","role":"SUPPORT","sightWardsBoughtInGame":0,"spell1Casts":159,"spell2Casts":22,"spell3Casts":31,"spell4Casts":7,"summoner1Casts":17,"summoner1Id":32,"summoner2Casts":3,"summoner2Id":21,"summonerId":"XWxjFn2yth1EqvyT72u4sjQ5GbnHxFji56_tTAHdFVngl2w","summonerLevel":142,"summonerName":"Gnomodav","teamEarlySurrendered":false,"teamId":100,"teamPosition":"","timeCCingOthers":26,"timePlayed":1317,"totalDamageDealt":76204,"totalDamageDealtToChampions":27080,"totalDamageShieldedOnTeammates":0,"totalDamageTaken":28975,"totalHeal":400,"totalHealsOnTeammates":0,"totalMinionsKilled":63,"totalTimeCCDealt":267,"totalTimeSpentDead":398,"totalUnitsHealed":1,"tripleKills":0,"trueDamageDealt":2023,"trueDamageDealtToChampions":1713,"trueDamageTaken":1492,"turretKills":0,"turretTakedowns":0,"turretsLost":4,"unrealKills":0,"visionScore":0,"visionWardsBoughtInGame":0,"wardsKilled":0,"wardsPlaced":0,"win":true},{"assists":27,"baronKills":0,"basicPings":0,"bountyLevel":5,"challenges":{"12AssistStreakCount":0,"abilityUses":298,"acesBefore15Minutes":0,"alliedJungleMonsterKills":0,"baronTakedowns":0,"blastConeOppositeOpponentCount":0,"bountyGold":1350,"buffsStolen":0,"completeSupportQuestInTime":0,"controlWardsPlaced":0,"damagePerMinute":2117.3585710625334,"damageTakenOnTeamPercentage":0.2599477146717618,"dancedWithRiftHerald":0,"deathsByEnemyChamps":13,"dodgeSkillShotsSmallWindow":2,"doubleAces":0,"dragonTakedowns":0,"earlyLaningPhaseGoldExpAdvantage":0,"effectiveHealAndShielding":681,"elderDragonKillsWithOpposingSoul":0,"elderDragonMultikills":0,"enemyChampionImmobilizations":13,"enemyJungleMonsterKills":0,"epicMonsterKillsNearEnemyJungler":0,"epicMonsterKillsWithin30SecondsOfSpawn":0,"epicMonsterSteals":0,"epicMonsterStolenWithoutSmite":0,"firstTurretKilledTime":536.5541941,"flawlessAces":0,"fullTeamTakedown":7,"gameLength":1317.6331278999999,"getTakedownsInAllLanesEarlyJungleAsLaner":0,"goldPerMinute":812.6803049450713,"hadOpenNexus":0,"highestChampionDamage":1,"immobilizeAndKillWithAlly":4,"initialBuffCount":0,"initialCrabCount":0,"jungleCsBefore10Minutes":0,"junglerTakedownsNearDamagedEpicMonster":0,"kTurretsDestroyedBeforePlatesFall":2,"kda":3.5384615384615383,"killAfterHiddenWithAlly":0,"killParticipation":0.6052631578947368,"killedChampTookFullTeamDamageSurvived":0,"killsNearEnemyTurret":6,"killsOnOtherLanesEarlyJungleAsLaner":0,"killsOnRecentlyHealedByAramPack":1,"killsUnderOwnTurret":3,"killsWithHelpFromEpicMonster":0,"knockEnemyIntoTeamAndKill":0,"landSkillShotsEarlyGame":23,"laneMinionsFirst10Minutes":23,"laningPhaseGoldExpAdvantage":0,"legendaryCount":0,"lostAnInhibitor":1,"maxCsAdvantageOnLaneOpponent":34,"maxKillDeficit":7,"maxLevelLeadLaneOpponent":2,"moreEnemyJungleThanOpponent":-20,"multiKillOneSpell":0,"multiTurretRiftHeraldCount":0,"multikills":5,"multikillsAfterAggressiveFlash":0,"mythicItemUsed":6673,"outerTurretExecutesBefore10Minutes":0,"outnumberedKills":2,"outnumberedNexusKill":0,"perfectDragonSoulsTaken":0,"perfectGame":0,"pickKillWithAlly":34,"poroExplosions":0,"quickCleanse":0,"quickFirstTurret":0,"quickSoloKills":0,"riftHeraldTakedowns":0,"saveAllyFromDeath":0,"scuttleCrabKills":0,"shortestTimeToAceFromFirstTakedown":13.133071900000004,"skillshotsDodged":53,"skillshotsHit":87,"snowballsHit":0,"soloBaronKills":0,"soloKills":0,"stealthWardsPlaced":0,"survivedSingleDigitHpCount":1,"survivedThreeImmobilizesInFight":0,"takedownOnFirstTurret":0,"takedowns":46,"takedownsAfterGainingLevelAdvantage":0,"takedownsBeforeJungleMinionSpawn":0,"takedownsFirstXMinutes":25,"takedownsInAlcove":0,"takedownsInEnemyFountain":0,"teamBaronKills":0,"teamDamagePercentage":0.28864331062252413,"teamElderDragonKills":0,"teamRiftHeraldKills":0,"threeWardsOneSweeperCount":0,"tookLargeDamageSurvived":0,"turretPlatesTaken":0,"turretTakedowns":4,"turretsTakenWithRiftHerald":0,"twentyMinionsIn3SecondsCount":0,"unseenRecalls":0,"visionScoreAdvantageLaneOpponent":-1,"visionScorePerMinute":0,"wardTakedowns":0,"wardTakedownsBefore20M":0,"wardsGuarded":0},"champExperience":25783,"champLevel":18,"championId":523,"championName":"Aphelios","championTransform":0,"consumablesPurchased":2,"damageDealtToBuildings":3699,"damageDealtToObjectives":3699,"damageDealtToTurrets":3699,"damageSelfMitigated":39315,"deaths":13,"detectorWardsPlaced":0,"doubleKills":4,"dragonKills":0,"eligibleForProgression":true,"firstBloodAssist":false,"firstBloodKill":false,"firstTowerAssist":true,"firstTowerKill":false,"gameEndedInEarlySurrender":false,"gameEndedInSurrender":false,"goldEarned":17846,"goldSpent":15350,"individualPosition":"Invalid","inhibitorKills":0,"inhibitorTakedowns":2,"inhibitorsLost":2,"item0":6673,"item1":3111,"item2":3085,"item3":3031,"item4":3072,"item5":3086,"item6":2052,"itemsPurchased":23,"killingSprees":5,"kills":19,"lane":"TOP","largestCriticalStrike":856,"largestKillingSpree":5,"largestMultiKill":3,"longestTimeSpentLiving":197,"magicDamageDealt":1423,"magicDamageDealtToChampions":836,"magicDamageTaken":21030,"neutralMinionsKilled":0,"nexusKills":1,"nexusLost":0,"nexusTakedowns":1,"objectivesStolen":0,"objectivesStolenAssists":0,"participantId":2,"pentaKills":0,"perks":{"statPerks":{"defense":5002,"flex":5008,"offense":5005},"styles":[{"description":"primaryStyle","selections":[{"perk":8005,"var1":3154,"var2":1760,"var3":1394},{"perk":8009,"var1":3230,"var2":0,"var3":0},{"perk":9103,"var1":8,"var2":30,"var3":0},{"perk":8014,"var1":1366,"var2":0,"var3":0}],"style":8000},{"description":"subStyle","selections":[{"perk":8233,"var1":7,"var2":50,"var3":0},{"perk":8236,"var1":28,"var2":0,"var3":0}],"style":8200}]},"physicalDamageDealt":114534,"physicalDamageDealtToChampions":45661,"physicalDamageTaken":20610,"profileIcon":1109,"puuid":"fCWK7q6SFtQIL69YLVao0Yzy-lPUu0kKkGM_oOfyRNu75mCm7nriSk-JMVXs3VgJxQkOPR6ATq5_wQ","quadraKills":0,"riotIdName":"","riotIdTagline":"","role":"SUPPORT","sightWardsBoughtInGame":0,"spell1Casts":101,"spell2Casts":189,"spell3Casts":0,"spell4Casts":8,"summoner1Casts":6,"summoner1Id":4,"summoner2Casts":8,"summoner2Id":7,"summonerId":"fAaHSE-B9LjrJL9v-Ej-iqWhXP7wd4iUGpPJoFZLxZQAMSQ","summonerLevel":264,"summonerName":"Drunky Waaagh","teamEarlySurrendered":false,"teamId":100,"teamPosition":"","timeCCingOthers":23,"timePlayed":1317,"totalDamageDealt":115958,"totalDamageDealtToChampions":46498,"totalDamageShieldedOnTeammates":0,"totalDamageTaken":43411,"totalHeal":7497,"totalHealsOnTeammates":681,"totalMinionsKilled":69,"totalTimeCCDealt":114,"totalTimeSpentDead":350,"totalUnitsHealed":4,"tripleKills":1,"trueDamageDealt":0,"trueDamageDealtToChampions":0,"trueDamageTaken":1770,"turretKills":3,"turretTakedowns":4,"turretsLost":4,"unrealKills":0,"visionScore":0,"visionWardsBoughtInGame":0,"wardsKilled":0,"wardsPlaced":0,"win":true},{"assists":25,"baronKills":0,"basicPings":0,"bountyLevel":0,"challenges":{"12AssistStreakCount":0,"abilityUses":107,"acesBefore15Minutes":0,"alliedJungleMonsterKills":0,"baronTakedowns":0,"blastConeOppositeOpponentCount":0,"bountyGold":600,"buffsStolen":0,"completeSupportQuestInTime":0,"controlWardsPlaced":0,"damagePerMinute":892.4573185247403,"damageTakenOnTeamPercentage":0.16102126791628593,"dancedWithRiftHerald":0,"deathsByEnemyChamps":12,"dodgeSkillShotsSmallWindow":0,"doubleAces":0,"dragonTakedowns":0,"earlyLaningPhaseGoldExpAdvantage":0,"effectiveHealAndShielding":0,"elderDragonKillsWithOpposingSoul":0,"elderDragonMultikills":0,"enemyChampionImmobilizations":38,"enemyJungleMonsterKills":0,"epicMonsterKillsNearEnemyJungler":0,"epicMonsterKillsWithin30SecondsOfSpawn":0,"epicMonsterSteals":0,"epicMonsterStolenWithoutSmite":0,"firstTurretKilledTime":536.5541941,"flawlessAces":0,"fullTeamTakedown":7,"gameLength":1317.6331278999999,"getTakedownsInAllLanesEarlyJungleAsLaner":0,"goldPerMinute":648.5456210974643,"hadOpenNexus":0,"immobilizeAndKillWithAlly":13,"initialBuffCount":0,"initialCrabCount":0,"jungleCsBefore10Minutes":0,"junglerTakedownsNearDamagedEpicMonster":0,"kTurretsDestroyedBeforePlatesFall":1,"kda":2.5,"killAfterHiddenWithAlly":1,"killParticipation":0.39473684210526316,"killedChampTookFullTeamDamageSurvived":0,"killsNearEnemyTurret":1,"killsOnOtherLanesEarlyJungleAsLaner":0,"killsOnRecentlyHealedByAramPack":1,"killsUnderOwnTurret":1,"killsWithHelpFromEpicMonster":0,"knockEnemyIntoTeamAndKill":0,"landSkillShotsEarlyGame":30,"laneMinionsFirst10Minutes":19,"laningPhaseGoldExpAdvantage":0,"legendaryCount":0,"lostAnInhibitor":1,"maxCsAdvantageOnLaneOpponent":15,"maxKillDeficit":7,"maxLevelLeadLaneOpponent":2,"moreEnemyJungleThanOpponent":-20,"multiKillOneSpell":0,"multiTurretRiftHeraldCount":0,"multikills":0,"multikillsAfterAggressiveFlash":0,"mythicItemUsed":6655,"outerTurretExecutesBefore10Minutes":0,"outnumberedKills":2,"outnumberedNexusKill":0,"perfectDragonSoulsTaken":0,"perfectGame":0,"pickKillWithAlly":22,"poroExplosions":0,"quickCleanse":0,"quickFirstTurret":0,"quickSoloKills":0,"riftHeraldTakedowns":0,"saveAllyFromDeath":0,"scuttleCrabKills":0,"shortestTimeToAceFromFirstTakedown":13.133071900000004,"skillshotsDodged":50,"skillshotsHit":72,"snowballsHit":4,"soloBaronKills":0,"soloKills":0,"stealthWardsPlaced":0,"survivedSingleDigitHpCount":0,"survivedThreeImmobilizesInFight":0,"takedownOnFirstTurret":0,"takedowns":30,"takedownsAfterGainingLevelAdvantage":0,"takedownsBeforeJungleMinionSpawn":0,"takedownsFirstXMinutes":17,"takedownsInAlcove":0,"takedownsInEnemyFountain":0,"teamBaronKills":0,"teamDamagePercentage":0.12166188501506937,"teamElderDragonKills":0,"teamRiftHeraldKills":0,"threeWardsOneSweeperCount":0,"tookLargeDamageSurvived":0,"turretPlatesTaken":0,"turretTakedowns":3,"turretsTakenWithRiftHerald":0,"twentyMinionsIn3SecondsCount":0,"unseenRecalls":0,"visionScoreAdvantageLaneOpponent":-1,"visionScorePerMinute":0,"wardTakedowns":0,"wardTakedownsBefore20M":0,"wardsGuarded":0},"champExperience":23799,"champLevel":18,"championId":518,"championName":"Neeko","championTransform":0,"consumablesPurchased":2,"damageDealtToBuildings":2226,"damageDealtToObjectives":2226,"damageDealtToTurrets":2226,"damageSelfMitigated":17684,"deaths":12,"detectorWardsPlaced":0,"doubleKills":0,"dragonKills":0,"eligibleForProgression":true,"firstBloodAssist":false,"firstBloodKill":false,"firstTowerAssist":false,"firstTowerKill":false,"gameEndedInEarlySurrender":false,"gameEndedInSurrender":false,"goldEarned":14242,"goldSpent":15200,"individualPosition":"Invalid","inhibitorKills":1,"inhibitorTakedowns":2,"inhibitorsLost":2,"item0":6655,"item1":3020,"item2":3115,"item3":4645,"item4":2031,"item5":1058,"item6":0,"itemsPurchased":19,"killingSprees":0,"kills":5,"lane":"TOP","largestCriticalStrike":233,"largestKillingSpree":0,"largestMultiKill":1,"longestTimeSpentLiving":228,"magicDamageDealt":50068,"magicDamageDealtToChampions":15705,"magicDamageTaken":10776,"neutralMinionsKilled":0,"nexusKills":0,"nexusLost":0,"nexusTakedowns":0,"objectivesStolen":0,"objectivesStolenAssists":0,"participantId":3,"pentaKills":0,"perks":{"statPerks":{"defense":5002,"flex":5008,"offense":5008},"styles":[{"description":"primaryStyle","selections":[{"perk":8230,"var1":12,"var2":0,"var3":0},{"perk":8275,"var1":19,"var2":0,"var3":0},{"perk":8233,"var1":10,"var2":10,"var3":0},{"perk":8236,"var1":48,"var2":0,"var3":0}],"style":8200},{"description":"subStyle","selections":[{"perk":8139,"var1":963,"var2":0,"var3":0},{"perk":8106,"var1":5,"var2":0,"var3":0}],"style":8100}]},"physicalDamageDealt":15427,"physicalDamageDealtToChampions":3353,"physicalDamageTaken":14661,"profileIcon":5410,"puuid":"e2Wo4PGAcQDEOWeyS1srrOR4eNTedZylmJ6ndc_Vwf2fGx-EB6uWTv00DE81jLJWSW0EECX2MIBxtw","quadraKills":0,"riotIdName":"","riotIdTagline":"","role":"SUPPORT","sightWardsBoughtInGame":0,"spell1Casts":38,"spell2Casts":20,"spell3Casts":37,"spell4Casts":12,"summoner1Casts":14,"summoner1Id":32,"summoner2Casts":5,"summoner2Id":4,"summonerId":"1a8IpqpoWY7pkoT0apG86oB9w_R88wSDTKVZc9Sr4jUTGxM","summonerLevel":560,"summonerName":"Quivindor","teamEarlySurrendered":false,"teamId":100,"teamPosition":"","timeCCingOthers":44,"timePlayed":1317,"totalDamageDealt":66200,"totalDamageDealtToChampions":19598,"totalDamageShieldedOnTeammates":0,"totalDamageTaken":26890,"totalHeal":2340,"totalHealsOnTeammates":0,"totalMinionsKilled":48,"totalTimeCCDealt":112,"totalTimeSpentDead":296,"totalUnitsHealed":1,"tripleKills":0,"trueDamageDealt":705,"trueDamageDealtToChampions":540,"trueDamageTaken":1452,"turretKills":0,"turretTakedowns":3,"turretsLost":4,"unrealKills":0,"visionScore":0,"visionWardsBoughtInGame":0,"wardsKilled":0,"wardsPlaced":0,"win":true},{"assists":21,"baronKills":0,"basicPings":0,"bountyLevel":1,"challenges":{"12AssistStreakCount":0,"abilityUses":275,"acesBefore15Minutes":0,"alliedJungleMonsterKills":0,"baronTakedowns":0,"blastConeOppositeOpponentCount":0,"bountyGold":1125,"buffsStolen":0,"completeSupportQuestInTime":0,"controlWardsPlaced":0,"damagePerMinute":1422.6106984441737,"damageTakenOnTeamPercentage":0.23217176851912386,"dancedWithRiftHerald":0,"deathsByEnemyChamps":10,"dodgeSkillShotsSmallWindow":1,"doubleAces":0,"dragonTakedowns":0,"earlyLaningPhaseGoldExpAdvantage":0,"effectiveHealAndShielding":0,"elderDragonKillsWithOpposingSoul":0,"elderDragonMultikills":0,"enemyChampionImmobilizations":80,"enemyJungleMonsterKills":0,"epicMonsterKillsNearEnemyJungler":0,"epicMonsterKillsWithin30SecondsOfSpawn":0,"epicMonsterSteals":0,"epicMonsterStolenWithoutSmite":0,"firstTurretKilledTime":536.5541941,"flawlessAces":0,"fullTeamTakedown":7,"gameLength":1317.6331278999999,"getTakedownsInAllLanesEarlyJungleAsLaner":0,"goldPerMinute":728.1236361655614,"hadOpenNexus":0,"immobilizeAndKillWithAlly":20,"initialBuffCount":0,"initialCrabCount":0,"jungleCsBefore10Minutes":0,"junglerTakedownsNearDamagedEpicMonster":0,"kTurretsDestroyedBeforePlatesFall":2,"kda":3.3,"killAfterHiddenWithAlly":8,"killParticipation":0.4342105263157895,"killedChampTookFullTeamDamageSurvived":0,"killsNearEnemyTurret":0,"killsOnOtherLanesEarlyJungleAsLaner":0,"killsOnRecentlyHealedByAramPack":0,"killsUnderOwnTurret":3,"killsWithHelpFromEpicMonster":0,"knockEnemyIntoTeamAndKill":22,"landSkillShotsEarlyGame":24,"laneMinionsFirst10Minutes":16,"laningPhaseGoldExpAdvantage":0,"legendaryCount":0,"lostAnInhibitor":1,"maxCsAdvantageOnLaneOpponent":5,"maxKillDeficit":7,"maxLevelLeadLaneOpponent":2,"moreEnemyJungleThanOpponent":-20,"multiKillOneSpell":0,"multiTurretRiftHeraldCount":0,"multikills":3,"multikillsAfterAggressiveFlash":0,"mythicItemUsed":4636,"outerTurretExecutesBefore10Minutes":0,"outnumberedKills":2,"outnumberedNexusKill":0,"perfectDragonSoulsTaken":0,"perfectGame":0,"pickKillWithAlly":24,"poroExplosions":0,"quickCleanse":0,"quickFirstTurret":0,"quickSoloKills":0,"riftHeraldTakedowns":0,"saveAllyFromDeath":0,"scuttleCrabKills":0,"shortestTimeToAceFromFirstTakedown":13.133071900000004,"skillshotsDodged":47,"skillshotsHit":53,"snowballsHit":0,"soloBaronKills":0,"soloKills":2,"stealthWardsPlaced":0,"survivedSingleDigitHpCount":0,"survivedThreeImmobilizesInFight":0,"takedownOnFirstTurret":1,"takedowns":33,"takedownsAfterGainingLevelAdvantage":0,"takedownsBeforeJungleMinionSpawn":0,"takedownsFirstXMinutes":22,"takedownsInAlcove":0,"takedownsInEnemyFountain":0,"teamBaronKills":0,"teamDamagePercentage":0.19393364323733162,"teamElderDragonKills":0,"teamRiftHeraldKills":0,"threeWardsOneSweeperCount":0,"tookLargeDamageSurvived":0,"turretPlatesTaken":0,"turretTakedowns":2,"turretsTakenWithRiftHerald":0,"twentyMinionsIn3SecondsCount":0,"unseenRecalls":0,"visionScoreAdvantageLaneOpponent":-1,"visionScorePerMinute":0,"wardTakedowns":0,"wardTakedownsBefore20M":0,"wardsGuarded":0},"champExperience":22069,"champLevel":18,"championId":79,"championName":"Gragas","championTransform":0,"consumablesPurchased":2,"damageDealtToBuildings":1691,"damageDealtToObjectives":1691,"damageDealtToTurrets":1691,"damageSelfMitigated":31837,"deaths":10,"detectorWardsPlaced":0,"doubleKills":3,"dragonKills":0,"eligibleForProgression":true,"firstBloodAssist":false,"firstBloodKill":false,"firstTowerAssist":false,"firstTowerKill":true,"gameEndedInEarlySurrender":false,"gameEndedInSurrender":false,"goldEarned":15989,"goldSpent":15960,"individualPosition":"Invalid","inhibitorKills":0,"inhibitorTakedowns":1,"inhibitorsLost":2,"item0":3020,"item1":3040,"item2":3089,"item3":4636,"item4":4645,"item5":4630,"item6":2052,"itemsPurchased":17,"killingSprees":4,"kills":12,"lane":"TOP","largestCriticalStrike":0,"largestKillingSpree":3,"largestMultiKill":2,"longestTimeSpentLiving":207,"magicDamageDealt":55337,"magicDamageDealtToChampions":28169,"magicDamageTaken":21862,"neutralMinionsKilled":0,"nexusKills":0,"nexusLost":0,"nexusTakedowns":0,"objectivesStolen":0,"objectivesStolenAssists":0,"participantId":4,"pentaKills":0,"perks":{"statPerks":{"defense":5003,"flex":5008,"offense":5008},"styles":[{"description":"primaryStyle","selections":[{"perk":8369,"var1":797,"var2":717,"var3":0},{"perk":8304,"var1":5,"var2":3,"var3":0},{"perk":8345,"var1":3,"var2":0,"var3":0},{"perk":8347,"var1":0,"var2":0,"var3":0}],"style":8300},{"description":"subStyle","selections":[{"perk":8226,"var1":250,"var2":626,"var3":0},{"perk":8210,"var1":14,"var2":0,"var3":0}],"style":8200}]},"physicalDamageDealt":1972,"physicalDamageDealtToChampions":1073,"physicalDamageTaken":15223,"profileIcon":4419,"puuid":"RMGAJeKP9eOfyXl0burUMaHFWmSxZLZU0J08dBCeUg6rHJn-DE8IlEGgAGLjd24uAVF01LqU6vk2Zw","quadraKills":0,"riotIdName":"","riotIdTagline":"","role":"SUPPORT","sightWardsBoughtInGame":0,"spell1Casts":163,"spell2Casts":34,"spell3Casts":68,"spell4Casts":10,"summoner1Casts":6,"summoner1Id":4,"summoner2Casts":7,"summoner2Id":14,"summonerId":"yPVnNKE1Ns2D_Rc0X3vL5zWKRKXzngcI3J0nnCAb6An6RHM","summonerLevel":301,"summonerName":"Fantasci","teamEarlySurrendered":false,"teamId":100,"teamPosition":"","timeCCingOthers":45,"timePlayed":1317,"totalDamageDealt":59307,"totalDamageDealtToChampions":31241,"totalDamageShieldedOnTeammates":0,"totalDamageTaken":38772,"totalHeal":11143,"totalHealsOnTeammates":0,"totalMinionsKilled":31,"totalTimeCCDealt":209,"totalTimeSpentDead":294,"totalUnitsHealed":1,"tripleKills":0,"trueDamageDealt":1998,"trueDamageDealtToChampions":1998,"trueDamageTaken":1687,"turretKills":1,"turretTakedowns":2,"turretsLost":4,"unrealKills":0,"visionScore":0,"visionWardsBoughtInGame":0,"wardsKilled":0,"wardsPlaced":0,"win":true},{"assists":31,"baronKills":0,"basicPings":4,"bountyLevel":0,"challenges":{"12AssistStreakCount":0,"abilityUses":164,"acesBefore15Minutes":0,"alliedJungleMonsterKills":0,"baronTakedowns":0,"blastConeOppositeOpponentCount":0,"bountyGold":300,"buffsStolen":0,"completeSupportQuestInTime":0,"controlWardsPlaced":0,"damagePerMinute":1670.0052922788998,"damageTakenOnTeamPercentage":0.17335574478406893,"dancedWithRiftHerald":0,"deathsByEnemyChamps":10,"dodgeSkillShotsSmallWindow":1,"doubleAces":0,"dragonTakedowns":0,"earlyLaningPhaseGoldExpAdvantage":0,"effectiveHealAndShielding":1824.538330078125,"elderDragonKillsWithOpposingSoul":0,"elderDragonMultikills":0,"enemyChampionImmobilizations":0,"enemyJungleMonsterKills":0,"epicMonsterKillsNearEnemyJungler":0,"epicMonsterKillsWithin30SecondsOfSpawn":0,"epicMonsterSteals":0,"epicMonsterStolenWithoutSmite":0,"firstTurretKilledTime":536.5541941,"flawlessAces":0,"fullTeamTakedown":7,"gameLength":1317.6331278999999,"getTakedownsInAllLanesEarlyJungleAsLaner":0,"goldPerMinute":797.143479478238,"hadOpenNexus":0,"immobilizeAndKillWithAlly":0,"initialBuffCount":0,"initialCrabCount":0,"jungleCsBefore10Minutes":0,"junglerTakedownsNearDamagedEpicMonster":0,"kTurretsDestroyedBeforePlatesFall":2,"kda":4.8,"killAfterHiddenWithAlly":9,"killParticipation":0.631578947368421,"killedChampTookFullTeamDamageSurvived":0,"killsNearEnemyTurret":2,"killsOnOtherLanesEarlyJungleAsLaner":0,"killsOnRecentlyHealedByAramPack":0,"killsUnderOwnTurret":4,"killsWithHelpFromEpicMonster":0,"knockEnemyIntoTeamAndKill":0,"landSkillShotsEarlyGame":5,"laneMinionsFirst10Minutes":30,"laningPhaseGoldExpAdvantage":0,"legendaryCount":0,"lostAnInhibitor":1,"maxCsAdvantageOnLaneOpponent":40,"maxKillDeficit":7,"maxLevelLeadLaneOpponent":2,"moreEnemyJungleThanOpponent":-20,"multiKillOneSpell":0,"multiTurretRiftHeraldCount":0,"multikills":6,"multikillsAfterAggressiveFlash":2,"mythicItemUsed":6672,"outerTurretExecutesBefore10Minutes":0,"outnumberedKills":2,"outnumberedNexusKill":0,"perfectDragonSoulsTaken":0,"perfectGame":0,"pickKillWithAlly":35,"poroExplosions":0,"quickCleanse":0,"quickFirstTurret":0,"quickSoloKills":0,"riftHeraldTakedowns":0,"saveAllyFromDeath":2,"scuttleCrabKills":0,"shortestTimeToAceFromFirstTakedown":13.133071900000004,"skillshotsDodged":41,"skillshotsHit":17,"snowballsHit":2,"soloBaronKills":0,"soloKills":0,"stealthWardsPlaced":0,"survivedSingleDigitHpCount":0,"survivedThreeImmobilizesInFight":0,"takedownOnFirstTurret":0,"takedowns":48,"takedownsAfterGainingLevelAdvantage":0,"takedownsBeforeJungleMinionSpawn":0,"takedownsFirstXMinutes":28,"takedownsInAlcove":0,"takedownsInEnemyFountain":0,"teamBaronKills":0,"teamDamagePercentage":0.2276590573313344,"teamElderDragonKills":0,"teamRiftHeraldKills":0,"threeWardsOneSweeperCount":0,"tookLargeDamageSurvived":0,"turretPlatesTaken":0,"turretTakedowns":4,"turretsTakenWithRiftHerald":0,"twentyMinionsIn3SecondsCount":0,"unseenRecalls":0,"visionScoreAdvantageLaneOpponent":-1,"visionScorePerMinute":0,"wardTakedowns":0,"wardTakedownsBefore20M":0,"wardsGuarded":0},"champExperience":25152,"champLevel":18,"championId":10,"championName":"Kayle","championTransform":0,"consumablesPurchased":0,"damageDealtToBuildings":2268,"damageDealtToObjectives":2268,"damageDealtToTurrets":2268,"damageSelfMitigated":16109,"deaths":10,"detectorWardsPlaced":0,"doubleKills":5,"dragonKills":0,"eligibleForProgression":true,"firstBloodAssist":false,"firstBloodKill":false,"firstTowerAssist":true,"firstTowerKill":false,"gameEndedInEarlySurrender":false,"gameEndedInSurrender":false,"goldEarned":17505,"goldSpent":17050,"individualPosition":"Invalid","inhibitorKills":1,"inhibitorTakedowns":2,"inhibitorsLost":2,"item0":6672,"item1":3153,"item2":3124,"item3":3091,"item4":3072,"item5":3006,"item6":0,"itemsPurchased":19,"killingSprees":6,"kills":17,"lane":"TOP","largestCriticalStrike":328,"largestKillingSpree":4,"largestMultiKill":3,"longestTimeSpentLiving":353,"magicDamageDealt":35036,"magicDamageDealtToChampions":10413,"magicDamageTaken":11111,"neutralMinionsKilled":0,"nexusKills":0,"nexusLost":0,"nexusTakedowns":0,"objectivesStolen":0,"objectivesStolenAssists":0,"participantId":5,"pentaKills":0,"perks":{"statPerks":{"defense":5002,"flex":5008,"offense":5005},"styles":[{"description":"primaryStyle","selections":[{"perk":8008,"var1":46,"var2":8,"var3":0},{"perk":8009,"var1":3962,"var2":0,"var3":0},{"perk":9104,"var1":7,"var2":10,"var3":0},{"perk":8014,"var1":1244,"var2":0,"var3":0}],"style":8000},{"description":"subStyle","selections":[{"perk":8139,"var1":1025,"var2":0,"var3":0},{"perk":8135,"var1":550,"var2":5,"var3":0}],"style":8100}]},"physicalDamageDealt":63753,"physicalDamageDealtToChampions":22766,"physicalDamageTaken":16926,"profileIcon":4905,"puuid":"pYYpa3eRU8O0fCkOU2mEcvCad-NMyRfZBkwfBAi0NzDB2__LfBLMlL-BfHWgqtqsBDyNQb4bzRkQfg","quadraKills":0,"riotIdName":"","riotIdTagline":"","role":"SUPPORT","sightWardsBoughtInGame":0,"spell1Casts":57,"spell2Casts":46,"spell3Casts":54,"spell4Casts":7,"summoner1Casts":6,"summoner1Id":32,"summoner2Casts":3,"summoner2Id":4,"summonerId":"wP-IFDBlyk-nNMOrQY-LhKxK4HpiQpPvE0HgoxtlIsL3QK0Q","summonerLevel":173,"summonerName":"Charmeleοn","teamEarlySurrendered":false,"teamId":100,"teamPosition":"","timeCCingOthers":6,"timePlayed":1317,"totalDamageDealt":136850,"totalDamageDealtToChampions":36674,"totalDamageShieldedOnTeammates":0,"totalDamageTaken":28950,"totalHeal":5939,"totalHealsOnTeammates":1824,"totalMinionsKilled":75,"totalTimeCCDealt":126,"totalTimeSpentDead":278,"totalUnitsHealed":5,"tripleKills":1,"trueDamageDealt":38060,"trueDamageDealtToChampions":3493,"trueDamageTaken":912,"turretKills":0,"turretTakedowns":4,"turretsLost":4,"unrealKills":0,"visionScore":0,"visionWardsBoughtInGame":0,"wardsKilled":0,"wardsPlaced":0,"win":true},{"assists":21,"baronKills":0,"basicPings":8,"bountyLevel":0,"challenges":{"12AssistStreakCount":0,"abilityUses":198,"acesBefore15Minutes":1,"alliedJungleMonsterKills":0,"baronTakedowns":0,"blastConeOppositeOpponentCount":0,"bountyGold":450,"buffsStolen":0,"completeSupportQuestInTime":0,"controlWardsPlaced":0,"damagePerMinute":1504.4958066472125,"damageTakenOnTeamPercentage":0.2008951627468939,"dancedWithRiftHerald":0,"deathsByEnemyChamps":10,"dodgeSkillShotsSmallWindow":3,"doubleAces":0,"dragonTakedowns":0,"earlyLaningPhaseGoldExpAdvantage":0,"effectiveHealAndShielding":0,"elderDragonKillsWithOpposingSoul":0,"elderDragonMultikills":0,"enemyChampionImmobilizations":2,"enemyJungleMonsterKills":0,"epicMonsterKillsNearEnemyJungler":0,"epicMonsterKillsWithin30SecondsOfSpawn":0,"epicMonsterSteals":0,"epicMonsterStolenWithoutSmite":0,"flawlessAces":2,"fullTeamTakedown":4,"gameLength":1317.6331278999999,"getTakedownsInAllLanesEarlyJungleAsLaner":0,"goldPerMinute":717.7000274260106,"hadOpenNexus":0,"immobilizeAndKillWithAlly":2,"initialBuffCount":0,"initialCrabCount":0,"jungleCsBefore10Minutes":0,"junglerTakedownsNearDamagedEpicMonster":0,"kTurretsDestroyedBeforePlatesFall":1,"kda":3.5,"killAfterHiddenWithAlly":11,"killParticipation":0.7777777777777778,"killedChampTookFullTeamDamageSurvived":0,"killsNearEnemyTurret":1,"killsOnOtherLanesEarlyJungleAsLaner":0,"killsOnRecentlyHealedByAramPack":0,"killsUnderOwnTurret":2,"killsWithHelpFromEpicMonster":0,"knockEnemyIntoTeamAndKill":2,"landSkillShotsEarlyGame":13,"laneMinionsFirst10Minutes":14,"laningPhaseGoldExpAdvantage":0,"legendaryCount":0,"lostAnInhibitor":0,"maxCsAdvantageOnLaneOpponent":1,"maxKillDeficit":0,"maxLevelLeadLaneOpponent":2,"moreEnemyJungleThanOpponent":-20,"multiKillOneSpell":0,"multiTurretRiftHeraldCount":0,"multikills":1,"multikillsAfterAggressiveFlash":0,"mythicItemUsed":4636,"outerTurretExecutesBefore10Minutes":0,"outnumberedKills":3,"outnumberedNexusKill":0,"perfectDragonSoulsTaken":0,"perfectGame":0,"pickKillWithAlly":22,"poroExplosions":0,"quickCleanse":0,"quickFirstTurret":0,"quickSoloKills":0,"riftHeraldTakedowns":0,"saveAllyFromDeath":0,"scuttleCrabKills":0,"shortestTimeToAceFromFirstTakedown":27.16031099999998,"skillshotsDodged":47,"skillshotsHit":32,"snowballsHit":11,"soloBaronKills":0,"soloKills":0,"stealthWardsPlaced":0,"survivedSingleDigitHpCount":0,"survivedThreeImmobilizesInFight":0,"takedownOnFirstTurret":1,"takedowns":35,"takedownsAfterGainingLevelAdvantage":1,"takedownsBeforeJungleMinionSpawn":0,"takedownsFirstXMinutes":22,"takedownsInAlcove":0,"takedownsInEnemyFountain":0,"teamBaronKills":0,"teamDamagePercentage":0.2080007678551026,"teamElderDragonKills":0,"teamRiftHeraldKills":0,"threeWardsOneSweeperCount":0,"tookLargeDamageSurvived":0,"turretPlatesTaken":0,"turretTakedowns":1,"turretsTakenWithRiftHerald":0,"twentyMinionsIn3SecondsCount":0,"unseenRecalls":0,"visionScoreAdvantageLaneOpponent":-1,"visionScorePerMinute":0,"wardTakedowns":0,"wardTakedownsBefore20M":0,"wardsGuarded":0},"champExperience":24297,"champLevel":18,"championId":102,"championName":"Shyvana","championTransform":0,"consumablesPurchased":2,"damageDealtToBuildings":320,"damageDealtToObjectives":320,"damageDealtToTurrets":320,"damageSelfMitigated":30173,"deaths":10,"detectorWardsPlaced":0,"doubleKills":1,"dragonKills":0,"eligibleForProgression":true,"firstBloodAssist":false,"firstBloodKill":false,"firstTowerAssist":false,"firstTowerKill":false,"gameEndedInEarlySurrender":false,"gameEndedInSurrender":false,"goldEarned":15761,"goldSpent":15650,"individualPosition":"Invalid","inhibitorKills":1,"inhibitorTakedowns":1,"inhibitorsLost":2,"item0":4645,"item1":3020,"item2":4636,"item3":3089,"item4":4628,"item5":3916,"item6":2052,"itemsPurchased":22,"killingSprees":6,"kills":14,"lane":"MIDDLE","largestCriticalStrike":0,"largestKillingSpree":3,"largestMultiKill":2,"longestTimeSpentLiving":252,"magicDamageDealt":61878,"magicDamageDealtToChampions":28933,"magicDamageTaken":19193,"neutralMinionsKilled":0,"nexusKills":0,"nexusLost":1,"nexusTakedowns":0,"objectivesStolen":0,"objectivesStolenAssists":0,"participantId":6,"pentaKills":0,"perks":{"statPerks":{"defense":5001,"flex":5008,"offense":5008},"styles":[{"description":"primaryStyle","selections":[{"perk":8128,"var1":2335,"var2":29,"var3":0},{"perk":8143,"var1":569,"var2":0,"var3":0},{"perk":8138,"var1":30,"var2":0,"var3":0},{"perk":8135,"var1":550,"var2":5,"var3":0}],"style":8100},{"description":"subStyle","selections":[{"perk":8210,"var1":29,"var2":0,"var3":0},{"perk":8275,"var1":36,"var2":0,"var3":0}],"style":8200}]},"physicalDamageDealt":7624,"physicalDamageDealtToChampions":2615,"physicalDamageTaken":13979,"profileIcon":5371,"puuid":"rgWIpBYEyQ8TC8wXyiJrIlXgSM1o77taGZp5bOzXhhOo4aDPcsgIbkHr9TSbpWdi1OM2S7TIVPGSGA","quadraKills":0,"riotIdName":"","riotIdTagline":"","role":"SUPPORT","sightWardsBoughtInGame":0,"spell1Casts":39,"spell2Casts":69,"spell3Casts":77,"spell4Casts":13,"summoner1Casts":5,"summoner1Id":4,"summoner2Casts":31,"summoner2Id":32,"summonerId":"7a_79ygAdnbk4cMC-k9LDHUe83BbW3rCJVJUPbOXbpnhrBnADoNnGoIW6w","summonerLevel":55,"summonerName":"Toolmes","teamEarlySurrendered":false,"teamId":200,"teamPosition":"","timeCCingOthers":0,"timePlayed":1317,"totalDamageDealt":74503,"totalDamageDealtToChampions":33039,"totalDamageShieldedOnTeammates":0,"totalDamageTaken":34617,"totalHeal":1919,"totalHealsOnTeammates":0,"totalMinionsKilled":35,"totalTimeCCDealt":0,"totalTimeSpentDead":286,"totalUnitsHealed":1,"tripleKills":0,"trueDamageDealt":5000,"trueDamageDealtToChampions":1490,"trueDamageTaken":1445,"turretKills":0,"turretTakedowns":1,"turretsLost":4,"unrealKills":0,"visionScore":0,"visionWardsBoughtInGame":0,"wardsKilled":0,"wardsPlaced":0,"win":false},{"assists":37,"baronKills":0,"basicPings":2,"bountyLevel":0,"challenges":{"12AssistStreakCount":2,"abilityUses":133,"acesBefore15Minutes":1,"alliedJungleMonsterKills":0,"baronTakedowns":0,"blastConeOppositeOpponentCount":0,"bountyGold":0,"buffsStolen":0,"completeSupportQuestInTime":0,"controlWardsPlaced":0,"damagePerMinute":950.1433183418067,"damageTakenOnTeamPercentage":0.22144562940702056,"dancedWithRiftHerald":0,"deathsByEnemyChamps":15,"dodgeSkillShotsSmallWindow":11,"doubleAces":0,"dragonTakedowns":0,"earlyLaningPhaseGoldExpAdvantage":0,"effectiveHealAndShielding":0,"elderDragonKillsWithOpposingSoul":0,"elderDragonMultikills":0,"enemyChampionImmobilizations":46,"enemyJungleMonsterKills":0,"epicMonsterKillsNearEnemyJungler":0,"epicMonsterKillsWithin30SecondsOfSpawn":0,"epicMonsterSteals":0,"epicMonsterStolenWithoutSmite":0,"flawlessAces":2,"fullTeamTakedown":4,"gameLength":1317.6331278999999,"getTakedownsInAllLanesEarlyJungleAsLaner":0,"goldPerMinute":600.6602201546698,"hadOpenNexus":0,"immobilizeAndKillWithAlly":13,"initialBuffCount":0,"initialCrabCount":0,"jungleCsBefore10Minutes":0,"junglerTakedownsNearDamagedEpicMonster":0,"kTurretsDestroyedBeforePlatesFall":2,"kda":2.7333333333333334,"killAfterHiddenWithAlly":8,"killParticipation":0.9111111111111111,"killedChampTookFullTeamDamageSurvived":0,"killsNearEnemyTurret":2,"killsOnOtherLanesEarlyJungleAsLaner":0,"killsOnRecentlyHealedByAramPack":0,"killsUnderOwnTurret":0,"killsWithHelpFromEpicMonster":0,"knockEnemyIntoTeamAndKill":0,"landSkillShotsEarlyGame":32,"laneMinionsFirst10Minutes":16,"laningPhaseGoldExpAdvantage":0,"legendaryCount":0,"lostAnInhibitor":0,"maxCsAdvantageOnLaneOpponent":1,"maxKillDeficit":0,"maxLevelLeadLaneOpponent":1,"moreEnemyJungleThanOpponent":-20,"multiKillOneSpell":0,"multiTurretRiftHeraldCount":0,"multikills":1,"multikillsAfterAggressiveFlash":0,"mythicItemUsed":4636,"outerTurretExecutesBefore10Minutes":0,"outnumberedKills":0,"outnumberedNexusKill":0,"perfectDragonSoulsTaken":0,"perfectGame":0,"pickKillWithAlly":24,"poroExplosions":0,"quickCleanse":0,"quickFirstTurret":0,"quickSoloKills":0,"riftHeraldTakedowns":0,"saveAllyFromDeath":0,"scuttleCrabKills":0,"shortestTimeToAceFromFirstTakedown":10.373371900000052,"skillshotsDodged":98,"skillshotsHit":53,"snowballsHit":9,"soloBaronKills":0,"soloKills":0,"stealthWardsPlaced":0,"survivedSingleDigitHpCount":0,"survivedThreeImmobilizesInFight":0,"takedownOnFirstTurret":1,"takedowns":41,"takedownsAfterGainingLevelAdvantage":0,"takedownsBeforeJungleMinionSpawn":1,"takedownsFirstXMinutes":33,"takedownsInAlcove":0,"takedownsInEnemyFountain":0,"teamBaronKills":0,"teamDamagePercentage":0.13135998047605935,"teamElderDragonKills":0,"teamRiftHeraldKills":0,"threeWardsOneSweeperCount":0,"tookLargeDamageSurvived":0,"turretPlatesTaken":0,"turretTakedowns":4,"turretsTakenWithRiftHerald":0,"twentyMinionsIn3SecondsCount":0,"unseenRecalls":0,"visionScoreAdvantageLaneOpponent":-1,"visionScorePerMinute":0,"wardTakedowns":0,"wardTakedownsBefore20M":0,"wardsGuarded":0},"champExperience":21939,"champLevel":18,"championId":20,"championName":"Nunu","championTransform":0,"consumablesPurchased":0,"damageDealtToBuildings":1748,"damageDealtToObjectives":1748,"damageDealtToTurrets":1748,"damageSelfMitigated":40950,"deaths":15,"detectorWardsPlaced":0,"doubleKills":1,"dragonKills":0,"eligibleForProgression":true,"firstBloodAssist":true,"firstBloodKill":false,"firstTowerAssist":false,"firstTowerKill":false,"gameEndedInEarlySurrender":false,"gameEndedInSurrender":false,"goldEarned":13190,"goldSpent":12950,"individualPosition":"Invalid","inhibitorKills":0,"inhibitorTakedowns":1,"inhibitorsLost":2,"item0":4636,"item1":3157,"item2":3111,"item3":4645,"item4":3065,"item5":0,"item6":2052,"itemsPurchased":21,"killingSprees":1,"kills":4,"lane":"TOP","largestCriticalStrike":0,"largestKillingSpree":2,"largestMultiKill":2,"longestTimeSpentLiving":193,"magicDamageDealt":36269,"magicDamageDealtToChampions":18831,"magicDamageTaken":14976,"neutralMinionsKilled":0,"nexusKills":0,"nexusLost":1,"nexusTakedowns":0,"objectivesStolen":0,"objectivesStolenAssists":0,"participantId":7,"pentaKills":0,"perks":{"statPerks":{"defense":5002,"flex":5008,"offense":5008},"styles":[{"description":"primaryStyle","selections":[{"perk":8128,"var1":975,"var2":18,"var3":0},{"perk":8126,"var1":477,"var2":0,"var3":0},{"perk":8138,"var1":30,"var2":0,"var3":0},{"perk":8105,"var1":13,"var2":5,"var3":0}],"style":8100},{"description":"subStyle","selections":[{"perk":8234,"var1":7722,"var2":0,"var3":0},{"perk":8237,"var1":419,"var2":0,"var3":0}],"style":8200}]},"physicalDamageDealt":1393,"physicalDamageDealtToChampions":727,"physicalDamageTaken":21561,"profileIcon":5369,"puuid":"A_b8QEtbmOqikQjNisk0upEsWTEG5vHWldVXdGklQpd4CRJIPHXt8H9wfi7aAW_C6I095NyBsWJSGA","quadraKills":0,"riotIdName":"","riotIdTagline":"","role":"SOLO","sightWardsBoughtInGame":0,"spell1Casts":12,"spell2Casts":51,"spell3Casts":60,"spell4Casts":10,"summoner1Casts":5,"summoner1Id":4,"summoner2Casts":19,"summoner2Id":32,"summonerId":"CBe4jjTQ5gJLwc0fuKtjDfPFlH315GA3LSGc51RkNZR2NC7WqBY6Y91DpA","summonerLevel":73,"summonerName":"InfinityJYD","teamEarlySurrendered":false,"teamId":200,"teamPosition":"","timeCCingOthers":37,"timePlayed":1317,"totalDamageDealt":44005,"totalDamageDealtToChampions":20865,"totalDamageShieldedOnTeammates":0,"totalDamageTaken":38158,"totalHeal":5399,"totalHealsOnTeammates":0,"totalMinionsKilled":31,"totalTimeCCDealt":231,"totalTimeSpentDead":390,"totalUnitsHealed":1,"tripleKills":0,"trueDamageDealt":6342,"trueDamageDealtToChampions":1307,"trueDamageTaken":1620,"turretKills":2,"turretTakedowns":4,"turretsLost":4,"unrealKills":0,"visionScore":0,"visionWardsBoughtInGame":0,"wardsKilled":0,"wardsPlaced":0,"win":false},{"assists":22,"baronKills":0,"basicPings":1,"bountyLevel":0,"challenges":{"12AssistStreakCount":0,"abilityUses":135,"acesBefore15Minutes":1,"alliedJungleMonsterKills":0,"baronTakedowns":0,"blastConeOppositeOpponentCount":0,"bountyGold":825,"buffsStolen":0,"completeSupportQuestInTime":0,"controlWardsPlaced":0,"damagePerMinute":1573.6652879468031,"damageTakenOnTeamPercentage":0.17369945270925946,"dancedWithRiftHerald":0,"deathsByEnemyChamps":8,"dodgeSkillShotsSmallWindow":6,"doubleAces":0,"dragonTakedowns":0,"earlyLaningPhaseGoldExpAdvantage":0,"effectiveHealAndShielding":0,"elderDragonKillsWithOpposingSoul":0,"elderDragonMultikills":0,"enemyChampionImmobilizations":0,"enemyJungleMonsterKills":0,"epicMonsterKillsNearEnemyJungler":0,"epicMonsterKillsWithin30SecondsOfSpawn":0,"epicMonsterSteals":0,"epicMonsterStolenWithoutSmite":0,"flawlessAces":2,"fullTeamTakedown":4,"gameLength":1317.6331278999999,"getTakedownsInAllLanesEarlyJungleAsLaner":0,"goldPerMinute":781.0037441075181,"hadOpenNexus":0,"immobilizeAndKillWithAlly":0,"initialBuffCount":0,"initialCrabCount":0,"jungleCsBefore10Minutes":0,"junglerTakedownsNearDamagedEpicMonster":0,"kTurretsDestroyedBeforePlatesFall":2,"kda":4.5,"killAfterHiddenWithAlly":10,"killParticipation":0.8,"killedChampTookFullTeamDamageSurvived":0,"killsNearEnemyTurret":4,"killsOnOtherLanesEarlyJungleAsLaner":0,"killsOnRecentlyHealedByAramPack":0,"killsUnderOwnTurret":4,"killsWithHelpFromEpicMonster":0,"knockEnemyIntoTeamAndKill":0,"landSkillShotsEarlyGame":17,"laneMinionsFirst10Minutes":18,"laningPhaseGoldExpAdvantage":0,"legendaryCount":0,"lostAnInhibitor":0,"maxCsAdvantageOnLaneOpponent":9,"maxKillDeficit":0,"maxLevelLeadLaneOpponent":1,"moreEnemyJungleThanOpponent":-20,"multiKillOneSpell":0,"multiTurretRiftHeraldCount":0,"multikills":2,"multikillsAfterAggressiveFlash":0,"mythicItemUsed":6692,"outerTurretExecutesBefore10Minutes":0,"outnumberedKills":6,"outnumberedNexusKill":0,"perfectDragonSoulsTaken":0,"perfectGame":0,"pickKillWithAlly":25,"poroExplosions":0,"quickCleanse":0,"quickFirstTurret":0,"quickSoloKills":0,"riftHeraldTakedowns":0,"saveAllyFromDeath":0,"scuttleCrabKills":0,"shortestTimeToAceFromFirstTakedown":10.373371900000052,"skillshotsDodged":71,"skillshotsHit":70,"snowballsHit":13,"soloBaronKills":0,"soloKills":0,"stealthWardsPlaced":0,"survivedSingleDigitHpCount":0,"survivedThreeImmobilizesInFight":2,"takedownOnFirstTurret":1,"takedowns":36,"takedownsAfterGainingLevelAdvantage":0,"takedownsBeforeJungleMinionSpawn":1,"takedownsFirstXMinutes":28,"takedownsInAlcove":0,"takedownsInEnemyFountain":0,"teamBaronKills":0,"teamDamagePercentage":0.21756364277897247,"teamElderDragonKills":0,"teamRiftHeraldKills":0,"threeWardsOneSweeperCount":0,"tookLargeDamageSurvived":0,"turretPlatesTaken":0,"turretTakedowns":3,"turretsTakenWithRiftHerald":0,"twentyMinionsIn3SecondsCount":0,"unseenRecalls":0,"visionScoreAdvantageLaneOpponent":-1,"visionScorePerMinute":0,"wardTakedowns":0,"wardTakedownsBefore20M":0,"wardsGuarded":0},"champExperience":23479,"champLevel":18,"championId":104,"championName":"Graves","championTransform":0,"consumablesPurchased":0,"damageDealtToBuildings":3810,"damageDealtToObjectives":3810,"damageDealtToTurrets":3810,"damageSelfMitigated":34924,"deaths":8,"detectorWardsPlaced":0,"doubleKills":2,"dragonKills":0,"eligibleForProgression":true,"firstBloodAssist":true,"firstBloodKill":false,"firstTowerAssist":false,"firstTowerKill":false,"gameEndedInEarlySurrender":false,"gameEndedInSurrender":false,"goldEarned":17151,"goldSpent":14450,"individualPosition":"Invalid","inhibitorKills":0,"inhibitorTakedowns":0,"inhibitorsLost":2,"item0":1031,"item1":6692,"item2":3111,"item3":3072,"item4":3156,"item5":6676,"item6":0,"itemsPurchased":16,"killingSprees":4,"kills":14,"lane":"MIDDLE","largestCriticalStrike":455,"largestKillingSpree":5,"largestMultiKill":2,"longestTimeSpentLiving":306,"magicDamageDealt":1932,"magicDamageDealtToChampions":1707,"magicDamageTaken":15005,"neutralMinionsKilled":0,"nexusKills":0,"nexusLost":1,"nexusTakedowns":0,"objectivesStolen":0,"objectivesStolenAssists":0,"participantId":8,"pentaKills":0,"perks":{"statPerks":{"defense":5002,"flex":5008,"offense":5005},"styles":[{"description":"primaryStyle","selections":[{"perk":8128,"var1":1561,"var2":25,"var3":0},{"perk":8143,"var1":956,"var2":0,"var3":0},{"perk":8138,"var1":18,"var2":0,"var3":0},{"perk":8135,"var1":550,"var2":5,"var3":0}],"style":8100},{"description":"subStyle","selections":[{"perk":9111,"var1":1585,"var2":360,"var3":0},{"perk":8014,"var1":896,"var2":0,"var3":0}],"style":8000}]},"physicalDamageDealt":94941,"physicalDamageDealtToChampions":31629,"physicalDamageTaken":13579,"profileIcon":4895,"puuid":"AfJnU8VZj-cpNDuhKFmluLnvZJgVxFR49OxlkBkBqRL-Y08V9W3IWFuT7FK0FFRDBaBWDa-lPttgdQ","quadraKills":0,"riotIdName":"","riotIdTagline":"","role":"SUPPORT","sightWardsBoughtInGame":0,"spell1Casts":59,"spell2Casts":24,"spell3Casts":38,"spell4Casts":14,"summoner1Casts":5,"summoner1Id":4,"summoner2Casts":21,"summoner2Id":32,"summonerId":"S7Y1qeRPF8TbVdlXE8PoCVLdOmhpIYDk4FYj4Xs8cSBppaQS7i3NWUOg9w","summonerLevel":546,"summonerName":"Newbie adcary","teamEarlySurrendered":false,"teamId":200,"teamPosition":"","timeCCingOthers":25,"timePlayed":1317,"totalDamageDealt":98095,"totalDamageDealtToChampions":34558,"totalDamageShieldedOnTeammates":0,"totalDamageTaken":29931,"totalHeal":3965,"totalHealsOnTeammates":0,"totalMinionsKilled":68,"totalTimeCCDealt":228,"totalTimeSpentDead":186,"totalUnitsHealed":1,"tripleKills":0,"trueDamageDealt":1220,"trueDamageDealtToChampions":1220,"trueDamageTaken":1345,"turretKills":1,"turretTakedowns":3,"turretsLost":4,"unrealKills":0,"visionScore":0,"visionWardsBoughtInGame":0,"wardsKilled":0,"wardsPlaced":0,"win":false},{"assists":29,"baronKills":0,"basicPings":1,"bountyLevel":0,"challenges":{"12AssistStreakCount":0,"abilityUses":161,"acesBefore15Minutes":1,"alliedJungleMonsterKills":0,"baronTakedowns":0,"blastConeOppositeOpponentCount":0,"bountyGold":900,"buffsStolen":0,"completeSupportQuestInTime":0,"controlWardsPlaced":0,"damagePerMinute":1529.3768907144067,"damageTakenOnTeamPercentage":0.23520554473396657,"dancedWithRiftHerald":0,"deathsByEnemyChamps":15,"dodgeSkillShotsSmallWindow":1,"doubleAces":0,"dragonTakedowns":0,"earlyLaningPhaseGoldExpAdvantage":0,"effectiveHealAndShielding":0,"elderDragonKillsWithOpposingSoul":0,"elderDragonMultikills":0,"enemyChampionImmobilizations":0,"enemyJungleMonsterKills":0,"epicMonsterKillsNearEnemyJungler":0,"epicMonsterKillsWithin30SecondsOfSpawn":0,"epicMonsterSteals":0,"epicMonsterStolenWithoutSmite":0,"flawlessAces":2,"fullTeamTakedown":4,"gameLength":1317.6331278999999,"getTakedownsInAllLanesEarlyJungleAsLaner":0,"goldPerMinute":673.5264934685619,"hadOpenNexus":0,"immobilizeAndKillWithAlly":0,"initialBuffCount":0,"initialCrabCount":0,"jungleCsBefore10Minutes":0,"junglerTakedownsNearDamagedEpicMonster":0,"kTurretsDestroyedBeforePlatesFall":1,"kda":2.6666666666666665,"killAfterHiddenWithAlly":15,"killParticipation":0.8888888888888888,"killedChampTookFullTeamDamageSurvived":0,"killsNearEnemyTurret":1,"killsOnOtherLanesEarlyJungleAsLaner":0,"killsOnRecentlyHealedByAramPack":0,"killsUnderOwnTurret":1,"killsWithHelpFromEpicMonster":0,"knockEnemyIntoTeamAndKill":0,"landSkillShotsEarlyGame":8,"laneMinionsFirst10Minutes":14,"laningPhaseGoldExpAdvantage":0,"legendaryCount":0,"lostAnInhibitor":0,"maxCsAdvantageOnLaneOpponent":1,"maxKillDeficit":0,"maxLevelLeadLaneOpponent":1,"moreEnemyJungleThanOpponent":-20,"multiKillOneSpell":0,"multiTurretRiftHeraldCount":0,"multikills":2,"multikillsAfterAggressiveFlash":0,"mythicItemUsed":6655,"outerTurretExecutesBefore10Minutes":0,"outnumberedKills":5,"outnumberedNexusKill":0,"perfectDragonSoulsTaken":0,"perfectGame":0,"pickKillWithAlly":23,"poroExplosions":0,"quickCleanse":0,"quickFirstTurret":0,"quickSoloKills":0,"riftHeraldTakedowns":0,"saveAllyFromDeath":0,"scuttleCrabKills":0,"shortestTimeToAceFromFirstTakedown":10.373371900000052,"skillshotsDodged":39,"skillshotsHit":35,"snowballsHit":7,"soloBaronKills":0,"soloKills":0,"stealthWardsPlaced":0,"survivedSingleDigitHpCount":0,"survivedThreeImmobilizesInFight":2,"takedownOnFirstTurret":0,"takedowns":40,"takedownsAfterGainingLevelAdvantage":0,"takedownsBeforeJungleMinionSpawn":1,"takedownsFirstXMinutes":30,"takedownsInAlcove":0,"takedownsInEnemyFountain":0,"teamBaronKills":0,"teamDamagePercentage":0.21144064755977054,"teamElderDragonKills":0,"teamRiftHeraldKills":0,"threeWardsOneSweeperCount":0,"tookLargeDamageSurvived":0,"turretPlatesTaken":0,"turretTakedowns":3,"turretsTakenWithRiftHerald":0,"twentyMinionsIn3SecondsCount":0,"unseenRecalls":0,"visionScoreAdvantageLaneOpponent":-1,"visionScorePerMinute":0,"wardTakedowns":0,"wardTakedownsBefore20M":0,"wardsGuarded":0},"champExperience":20243,"champLevel":18,"championId":38,"championName":"Kassadin","championTransform":0,"consumablesPurchased":1,"damageDealtToBuildings":2303,"damageDealtToObjectives":2303,"damageDealtToTurrets":2303,"damageSelfMitigated":38322,"deaths":15,"detectorWardsPlaced":0,"doubleKills":2,"dragonKills":0,"eligibleForProgression":true,"firstBloodAssist":true,"firstBloodKill":false,"firstTowerAssist":false,"firstTowerKill":false,"gameEndedInEarlySurrender":false,"gameEndedInSurrender":false,"goldEarned":14791,"goldSpent":14500,"individualPosition":"Invalid","inhibitorKills":0,"inhibitorTakedowns":0,"inhibitorsLost":2,"item0":3040,"item1":3112,"item2":6655,"item3":3020,"item4":4645,"item5":3089,"item6":0,"itemsPurchased":19,"killingSprees":3,"kills":11,"lane":"MIDDLE","largestCriticalStrike":0,"largestKillingSpree":2,"largestMultiKill":2,"longestTimeSpentLiving":124,"magicDamageDealt":47834,"magicDamageDealtToChampions":31428,"magicDamageTaken":16921,"neutralMinionsKilled":0,"nexusKills":0,"nexusLost":1,"nexusTakedowns":0,"objectivesStolen":0,"objectivesStolenAssists":0,"participantId":9,"pentaKills":0,"perks":{"statPerks":{"defense":5002,"flex":5008,"offense":5007},"styles":[{"description":"primaryStyle","selections":[{"perk":8229,"var1":1718,"var2":0,"var3":0},{"perk":8226,"var1":250,"var2":544,"var3":0},{"perk":8210,"var1":20,"var2":0,"var3":0},{"perk":8237,"var1":460,"var2":0,"var3":0}],"style":8200},{"description":"subStyle","selections":[{"perk":8451,"var1":254,"var2":0,"var3":0},{"perk":8429,"var1":63,"var2":13,"var3":12}],"style":8400}]},"physicalDamageDealt":4255,"physicalDamageDealtToChampions":1322,"physicalDamageTaken":21694,"profileIcon":1627,"puuid":"bvxrxmuPyv8PjLzrV_fHRrjY0QEuRQ7XjAwA2fDm8Iu0A0xfKrnRBNehrXJx3I3rSMnfmUN3y3PrBg","quadraKills":0,"riotIdName":"","riotIdTagline":"","role":"SUPPORT","sightWardsBoughtInGame":0,"spell1Casts":48,"spell2Casts":31,"spell3Casts":39,"spell4Casts":43,"summoner1Casts":19,"summoner1Id":32,"summoner2Casts":5,"summoner2Id":4,"summonerId":"f23ogekZDjcWhGzrpyG_DPTmGUSFE19Y82BIF9FMpC4OUgI","summonerLevel":240,"summonerName":"karò","teamEarlySurrendered":false,"teamId":200,"teamPosition":"","timeCCingOthers":23,"timePlayed":1317,"totalDamageDealt":53020,"totalDamageDealtToChampions":33585,"totalDamageShieldedOnTeammates":0,"totalDamageTaken":40529,"totalHeal":2664,"totalHealsOnTeammates":0,"totalMinionsKilled":21,"totalTimeCCDealt":121,"totalTimeSpentDead":386,"totalUnitsHealed":1,"tripleKills":0,"trueDamageDealt":930,"trueDamageDealtToChampions":835,"trueDamageTaken":1914,"turretKills":1,"turretTakedowns":3,"turretsLost":4,"unrealKills":0,"visionScore":0,"visionWardsBoughtInGame":0,"wardsKilled":0,"wardsPlaced":0,"win":false},{"assists":29,"baronKills":0,"basicPings":0,"bountyLevel":0,"challenges":{"12AssistStreakCount":0,"abilityUses":142,"acesBefore15Minutes":1,"alliedJungleMonsterKills":0,"baronTakedowns":0,"blastConeOppositeOpponentCount":0,"bountyGold":1050,"buffsStolen":0,"completeSupportQuestInTime":0,"controlWardsPlaced":0,"damagePerMinute":1675.4449110341016,"damageTakenOnTeamPercentage":0.1687542104028595,"dancedWithRiftHerald":0,"deathsByEnemyChamps":13,"dodgeSkillShotsSmallWindow":4,"doubleAces":0,"dragonTakedowns":0,"earlyLaningPhaseGoldExpAdvantage":0,"effectiveHealAndShielding":0,"elderDragonKillsWithOpposingSoul":0,"elderDragonMultikills":0,"enemyChampionImmobilizations":0,"enemyJungleMonsterKills":0,"epicMonsterKillsNearEnemyJungler":0,"epicMonsterKillsWithin30SecondsOfSpawn":0,"epicMonsterSteals":0,"epicMonsterStolenWithoutSmite":0,"flawlessAces":2,"fullTeamTakedown":4,"gameLength":1317.6331278999999,"getTakedownsInAllLanesEarlyJungleAsLaner":0,"goldPerMinute":836.6863291886426,"hadOpenNexus":0,"immobilizeAndKillWithAlly":0,"initialBuffCount":0,"initialCrabCount":0,"jungleCsBefore10Minutes":0,"junglerTakedownsNearDamagedEpicMonster":0,"kTurretsDestroyedBeforePlatesFall":2,"kda":3.5384615384615383,"killAfterHiddenWithAlly":19,"killParticipation":1.0222222222222221,"killedChampTookFullTeamDamageSurvived":0,"killsNearEnemyTurret":1,"killsOnOtherLanesEarlyJungleAsLaner":0,"killsOnRecentlyHealedByAramPack":0,"killsUnderOwnTurret":5,"killsWithHelpFromEpicMonster":0,"knockEnemyIntoTeamAndKill":0,"landSkillShotsEarlyGame":23,"laneMinionsFirst10Minutes":37,"laningPhaseGoldExpAdvantage":0,"legendaryCount":0,"lostAnInhibitor":0,"maxCsAdvantageOnLaneOpponent":40,"maxKillDeficit":0,"maxLevelLeadLaneOpponent":2,"moreEnemyJungleThanOpponent":-20,"multiKillOneSpell":0,"multiTurretRiftHeraldCount":0,"multikills":5,"multikillsAfterAggressiveFlash":2,"mythicItemUsed":6672,"outerTurretExecutesBefore10Minutes":0,"outnumberedKills":4,"outnumberedNexusKill":0,"perfectDragonSoulsTaken":0,"perfectGame":0,"pickKillWithAlly":26,"poroExplosions":0,"quickCleanse":0,"quickFirstTurret":0,"quickSoloKills":0,"riftHeraldTakedowns":0,"saveAllyFromDeath":0,"scuttleCrabKills":0,"shortestTimeToAceFromFirstTakedown":10.373371900000052,"skillshotsDodged":44,"skillshotsHit":76,"snowballsHit":0,"soloBaronKills":0,"soloKills":0,"stealthWardsPlaced":0,"survivedSingleDigitHpCount":0,"survivedThreeImmobilizesInFight":2,"takedownOnFirstTurret":1,"takedowns":46,"takedownsAfterGainingLevelAdvantage":2,"takedownsBeforeJungleMinionSpawn":1,"takedownsFirstXMinutes":30,"takedownsInAlcove":0,"takedownsInEnemyFountain":0,"teamBaronKills":0,"teamDamagePercentage":0.231634961330095,"teamElderDragonKills":0,"teamRiftHeraldKills":0,"threeWardsOneSweeperCount":0,"tookLargeDamageSurvived":0,"turretPlatesTaken":0,"turretTakedowns":2,"turretsTakenWithRiftHerald":0,"twentyMinionsIn3SecondsCount":0,"unseenRecalls":0,"visionScoreAdvantageLaneOpponent":-1,"visionScorePerMinute":0,"wardTakedowns":0,"wardTakedownsBefore20M":0,"wardsGuarded":0},"champExperience":23899,"champLevel":18,"championId":15,"championName":"Sivir","championTransform":0,"consumablesPurchased":2,"damageDealtToBuildings":1743,"damageDealtToObjectives":1743,"damageDealtToTurrets":1743,"damageSelfMitigated":13285,"deaths":13,"detectorWardsPlaced":0,"doubleKills":4,"dragonKills":0,"eligibleForProgression":true,"firstBloodAssist":false,"firstBloodKill":true,"firstTowerAssist":false,"firstTowerKill":false,"gameEndedInEarlySurrender":false,"gameEndedInSurrender":false,"goldEarned":18374,"goldSpent":17600,"individualPosition":"Invalid","inhibitorKills":1,"inhibitorTakedowns":1,"inhibitorsLost":2,"item0":6672,"item1":1053,"item2":3046,"item3":3031,"item4":3004,"item5":6694,"item6":0,"itemsPurchased":18,"killingSprees":5,"kills":17,"lane":"MIDDLE","largestCriticalStrike":828,"largestKillingSpree":4,"largestMultiKill":3,"longestTimeSpentLiving":203,"magicDamageDealt":0,"magicDamageDealtToChampions":0,"magicDamageTaken":14247,"neutralMinionsKilled":0,"nexusKills":0,"nexusLost":1,"nexusTakedowns":0,"objectivesStolen":0,"objectivesStolenAssists":0,"participantId":10,"pentaKills":0,"perks":{"statPerks":{"defense":5002,"flex":5008,"offense":5005},"styles":[{"description":"primaryStyle","selections":[{"perk":8128,"var1":1751,"var2":29,"var3":0},{"perk":8139,"var1":1466,"var2":0,"var3":0},{"perk":8138,"var1":18,"var2":0,"var3":0},{"perk":8135,"var1":550,"var2":5,"var3":0}],"style":8100},{"description":"subStyle","selections":[{"perk":8009,"var1":3472,"var2":0,"var3":0},{"perk":8014,"var1":1128,"var2":0,"var3":0}],"style":8000}]},"physicalDamageDealt":130721,"physicalDamageDealtToChampions":34625,"physicalDamageTaken":13705,"profileIcon":5414,"puuid":"nor02xlFnxQbf-rUDK9ElPt8rZBLX2027oxC66JkoyDK74pJA9TArWrY66jrQtaYxMiaZwpDinv78g","quadraKills":0,"riotIdName":"","riotIdTagline":"","role":"DUO","sightWardsBoughtInGame":0,"spell1Casts":59,"spell2Casts":49,"spell3Casts":26,"spell4Casts":8,"summoner1Casts":4,"summoner1Id":4,"summoner2Casts":2,"summoner2Id":1,"summonerId":"KaBfwWdFmFKtCT8u3mFochc06sqS8HlFEhqU9YpkBpZLMvA","summonerLevel":420,"summonerName":"Shyim","teamEarlySurrendered":false,"teamId":200,"teamPosition":"","timeCCingOthers":0,"timePlayed":1317,"totalDamageDealt":137609,"totalDamageDealtToChampions":36793,"totalDamageShieldedOnTeammates":0,"totalDamageTaken":29079,"totalHeal":4130,"totalHealsOnTeammates":0,"totalMinionsKilled":100,"totalTimeCCDealt":51,"totalTimeSpentDead":348,"totalUnitsHealed":1,"tripleKills":1,"trueDamageDealt":6887,"trueDamageDealtToChampions":2168,"trueDamageTaken":1126,"turretKills":0,"turretTakedowns":2,"turretsLost":4,"unrealKills":0,"visionScore":0,"visionWardsBoughtInGame":0,"wardsKilled":0,"wardsPlaced":0,"win":false}],"platformId":"EUW1","queueId":450,"teams":[{"bans":[],"objectives":{"baron":{"first":false,"kills":0},"champion":{"first":false,"kills":61},"dragon":{"first":false,"kills":0},"inhibitor":{"first":true,"kills":2},"riftHerald":{"first":false,"kills":0},"tower":{"first":true,"kills":4}},"teamId":100,"win":true},{"bans":[],"objectives":{"baron":{"first":false,"kills":0},"champion":{"first":true,"kills":60},"dragon":{"first":false,"kills":0},"inhibitor":{"first":false,"kills":2},"riftHerald":{"first":false,"kills":0},"tower":{"first":false,"kills":4}},"teamId":200,"win":false}],"tournamentCode":""}}